alitop-0.2.dist-info/DESCRIPTION.rst
alitop-0.2.dist-info/METADATA
alitop-0.2.dist-info/RECORD
alitop-0.2.dist-info/WHEEL
alitop-0.2.dist-info/metadata.json
alitop-0.2.dist-info/top_level.txt
top/__init__.py
top/api/__init__.py
top/api/base.py
top/api/rest/AftersaleGetRequest.py
top/api/rest/AppipGetRequest.py
top/api/rest/AppstoreSubscribeGetRequest.py
top/api/rest/AreasGetRequest.py
top/api/rest/CategoryrecommendItemsGetRequest.py
top/api/rest/DeliveryTemplateAddRequest.py
top/api/rest/DeliveryTemplateDeleteRequest.py
top/api/rest/DeliveryTemplateGetRequest.py
top/api/rest/DeliveryTemplateUpdateRequest.py
top/api/rest/DeliveryTemplatesGetRequest.py
top/api/rest/FenxiaoCooperationAuditRequest.py
top/api/rest/FenxiaoCooperationGetRequest.py
top/api/rest/FenxiaoCooperationProductcatAddRequest.py
top/api/rest/FenxiaoCooperationTerminateRequest.py
top/api/rest/FenxiaoCooperationUpdateRequest.py
top/api/rest/FenxiaoDealerRequisitionorderAgreeRequest.py
top/api/rest/FenxiaoDealerRequisitionorderCloseRequest.py
top/api/rest/FenxiaoDealerRequisitionorderCreateRequest.py
top/api/rest/FenxiaoDealerRequisitionorderGetRequest.py
top/api/rest/FenxiaoDealerRequisitionorderModifyRequest.py
top/api/rest/FenxiaoDealerRequisitionorderQueryRequest.py
top/api/rest/FenxiaoDealerRequisitionorderRefuseRequest.py
top/api/rest/FenxiaoDealerRequisitionorderRemarkUpdateRequest.py
top/api/rest/FenxiaoDiscountAddRequest.py
top/api/rest/FenxiaoDiscountUpdateRequest.py
top/api/rest/FenxiaoDiscountsGetRequest.py
top/api/rest/FenxiaoDistributorItemsGetRequest.py
top/api/rest/FenxiaoDistributorProductsGetRequest.py
top/api/rest/FenxiaoDistributorsGetRequest.py
top/api/rest/FenxiaoGradeAddRequest.py
top/api/rest/FenxiaoGradeDeleteRequest.py
top/api/rest/FenxiaoGradeUpdateRequest.py
top/api/rest/FenxiaoGradesGetRequest.py
top/api/rest/FenxiaoLoginUserGetRequest.py
top/api/rest/FenxiaoOrderCloseRequest.py
top/api/rest/FenxiaoOrderConfirmPaidRequest.py
top/api/rest/FenxiaoOrderMessageAddRequest.py
top/api/rest/FenxiaoOrderRemarkUpdateRequest.py
top/api/rest/FenxiaoOrdersGetRequest.py
top/api/rest/FenxiaoProductAddRequest.py
