Metadata-Version: 2.0
Name: alitop
Version: 0.2
Summary: taobao open platform SDK
Home-page: https://open.taobao.com
Author: zhangjinjie
Author-email: zhangjinjie@yimian.com
License: MIT
Platform: UNKNOWN
